awesome_library/__init__.py
awesome_library/awesome.py
awesome_library-1.3.3.dist-info/METADATA
awesome_library-1.3.3.dist-info/WHEEL
awesome_library-1.3.3.dist-info/RECORD
