Metadata-Version: 2.1
Name: awesome-library
Version: 1.3.3
Summary: Awesome library to interact with the awesome dynamodb inside the awesome docker container
Author: christian.meister
Author-email: christianhanno.meister@gmail.com
Requires-Python: >=3.11,<4.0
Classifier: Programming Language :: Python :: 3
Classifier: Programming Language :: Python :: 3.11
Requires-Dist: boto3 (>=1.28.21,<2.0.0)
Requires-Dist: pandas (>=2.0.3,<3.0.0)
Requires-Dist: pydriller (>=2.5,<3.0)
